archlens-0.2.9.data/data/config.schema.json
archlens-0.2.9.data/data/config.template.json
src/__init__.py
src/cli_interface.py
src/config.schema.json
src/config.template.json
src/main.py
src/core/__init__.py
src/core/bt_file.py
src/core/bt_graph.py
src/core/bt_module.py
src/git_integration/__init__.py
src/git_integration/fetch_git.py
src/providers/__init__.py
src/providers/json/__init__.py
src/providers/json/json_render.py
src/providers/plantuml/__init__.py
src/providers/plantuml/pu_render.py
src/utils/__init__.py
src/utils/config_manager_singleton.py
src/utils/functions.py
src/utils/path_manager_singleton.py
src/views/__init__.py
src/views/utils.py
src/views/view_entities.py
src/views/view_manager.py
archlens-0.2.9.dist-info/METADATA
archlens-0.2.9.dist-info/WHEEL
archlens-0.2.9.dist-info/entry_points.txt
archlens-0.2.9.dist-info/top_level.txt
archlens-0.2.9.dist-info/RECORD
